baynext_py/__init__.py
baynext_py/_hooks/__init__.py
baynext_py/_hooks/registration.py
baynext_py/_hooks/sdkhooks.py
baynext_py/_hooks/types.py
baynext_py/_version.py
baynext_py/basesdk.py
baynext_py/errors/__init__.py
baynext_py/errors/baynextdefaulterror.py
baynext_py/errors/baynexterror.py
baynext_py/errors/httpvalidationerror.py
baynext_py/errors/no_response_error.py
baynext_py/errors/responsevalidationerror.py
baynext_py/httpclient.py
baynext_py/models/__init__.py
baynext_py/models/list_user_projects_v1_projects_getop.py
baynext_py/models/projectcreate.py
baynext_py/models/projectcreated.py
baynext_py/models/projectpublic.py
baynext_py/models/security.py
baynext_py/models/user.py
baynext_py/models/validationerror.py
baynext_py/projects.py
baynext_py/py.typed
baynext_py/sdk.py
baynext_py/sdkconfiguration.py
baynext_py/types/__init__.py
baynext_py/types/basemodel.py
baynext_py/user_sdk.py
baynext_py/utils/__init__.py
baynext_py/utils/annotations.py
baynext_py/utils/datetimes.py
baynext_py/utils/enums.py
baynext_py/utils/eventstreaming.py
baynext_py/utils/forms.py
baynext_py/utils/headers.py
baynext_py/utils/logger.py
baynext_py/utils/metadata.py
baynext_py/utils/queryparams.py
baynext_py/utils/requestbodies.py
baynext_py/utils/retries.py
baynext_py/utils/security.py
baynext_py/utils/serializers.py
baynext_py/utils/unmarshal_json_response.py
baynext_py/utils/url.py
baynext_py/utils/values.py
baynext_py-0.1.2.dist-info/METADATA
baynext_py-0.1.2.dist-info/WHEEL
baynext_py-0.1.2.dist-info/RECORD
